authc/__init__.py
authc-0.3.2.dist-info/METADATA
authc-0.3.2.dist-info/WHEEL
authc-0.3.2.dist-info/entry_points.txt
authc-0.3.2.dist-info/top_level.txt
authc-0.3.2.dist-info/RECORD
