Metadata-Version: 2.1
Name: authc
Version: 0.3.2
Summary: For authentication.
Home-page: https://github.com/
Author: 2kpwkoczw
Author-email: r2fscg@gmail.com
Classifier: Programming Language :: Python :: 3
Classifier: License :: OSI Approved :: MIT License
Classifier: Operating System :: OS Independent
Requires-Dist: codefast
